Workbook

Sheet README
A1: FootureX — каталог цен BX-013 и шаблон финансовой модели
A2: Файл не содержит прогнозов: выручка, пользователи, инвестиции и окупаемость не заданы.
A4: Лист | B4: Содержание | C4: Статус данных
A5: Каталог BX-013 | B5: Цены пакетов FTXcoin, Premium Pass, игровых наборов, лиг (синий шрифт — значения документа) | C5: Документ BX-013 v1.0
A6: Расчёты по каталогу | B6: Цена 1 FTXcoin по пакетам, долларовый эквивалент наборов, распределение взносов лиги | C6: Расчёт по данным BX (формулы)
A7: Драйверы (шаблон) | B7: Дерево драйверов на 5 лет: пустые жёлтые ячейки заполняет руководство | C7: Требуется подтверждение
A8: Классификация | B8: Разграничение: реальные данные / расчёт / требует подтверждения | C8: —
A10: Правила | B10: Revenue = реальные платежи через Telegram Stars / TON. Sink (расход валюты) ≠ выручка. Оборот между пользователями ≠ выручка платформы. | C10: BX-013
B11: Игровые показатели не переносятся на всю компанию FootureX Uzbekistan. | C11: Консолидированное ТЗ
B12: Комиссии Telegram/TON и налоги в BX-013 не указаны — в шаблоне вынесены отдельными вводами. | C12: Требуется подтверждение

Sheet Каталог BX-013
A1: Утверждённый каталог услуг и цен
A2: BX-013 Approved Services Catalog v1.0 (июнь 2026) — заменяет цены BX-010
A4: Пакеты FTXcoin | B4: Кол-во FTXcoin | C4: Цена, USD
A5: Пакет 30 | B5: 30 | C5: 1.99
A6: Пакет 60 | B6: 60 | C6: 3.99
A7: Пакет 90 | B7: 90 | C7: 5.99
A8: Пакет 150 | B8: 150 | C8: 9.5
A9: Пакет 400 | B9: 400 | C9: 24.99
A10: Пакет 120 исключён из каталога
A12: Battle Pass | B12: Цена, USD | C12: Дней в сезоне | D12: Уровней
A13: Free Pass | B13: 0 | C13: 14 | D13: 100
A14: Premium Pass | B14: 3.99 | C14: 14 | D14: 100
A16: Игровые наборы | B16: Цена | C16: Валюта | D16: Кол-во
A17: Free Pack | B17: каждые 24 ч | C17: —
A18: Common Pack | B18: 200 Coins | C18: Coins | D18: 200
A19: Uncommon Pack | B19: 800 Coins | C19: Coins | D19: 800
A20: Rare Pack | B20: 39 FTXcoin | C20: FTXcoin | D20: 39
A21: Epic Pack | B21: 59 FTXcoin | C21: FTXcoin | D21: 59
A22: Legendary Pack | B22: 89 FTXcoin | C22: FTXcoin | D22: 89
A23: Immortal Pack | B23: 139 FTXcoin | C23: FTXcoin | D23: 139
A24: Elite Pack | B24: 149 FTXcoin | C24: FTXcoin | D24: 149
A25: Create Player | B25: 30 FTXcoin | C25: FTXcoin | D25: 30
A27: Лиги | B27: Создание, FTXcoin | C27: Взнос за 7 дней | D27: Создателю | E27: Призовой фонд | F27: Казна
A28: Системные (ранги 19–100) | B28: 0 | C28: 0 | D28: 0 | E28: 0 | F28: 0
A29: Fan League | B29: 69 | C29: 5 | D29: 2 | E29: 2 | F29: 1
A30: Pro League | B30: 109 | C30: 8 | D30: 3 | E30: 3 | F30: 2
A31: Master League | B31: 149 | C31: 12 | D31: 5 | E31: 5 | F31: 2
A33: Доп. места | B33: 4 | C33: за FTXcoin | D33: 20 | E33: лимит мест | F33: 48
A35: Исключено: вывод FTXcoin в деньги; конвертация Coins → FTXcoin; нечестные лутбоксы; ставки.

Sheet Расчёты по каталогу
A1: Расчёты только по ценам BX-013
A2: Формулы ссылаются на лист «Каталог BX-013». Без допущений об объёмах.
A4: Пакет | B4: FTXcoin | C4: USD | D4: USD за 1 FTXcoin | E4: FTXcoin за 1 USD
A5: ='Каталог BX-013'!A5 -> Пакет 30 | B5: ='Каталог BX-013'!B5 -> 30 | C5: ='Каталог BX-013'!C5 -> 1.99 | D5: =C5/B5 -> 0.066333333 | E5: =B5/C5 -> 15.075377
A6: ='Каталог BX-013'!A6 -> Пакет 60 | B6: ='Каталог BX-013'!B6 -> 60 | C6: ='Каталог BX-013'!C6 -> 3.99 | D6: =C6/B6 -> 0.0665 | E6: =B6/C6 -> 15.037594
A7: ='Каталог BX-013'!A7 -> Пакет 90 | B7: ='Каталог BX-013'!B7 -> 90 | C7: ='Каталог BX-013'!C7 -> 5.99 | D7: =C7/B7 -> 0.066555556 | E7: =B7/C7 -> 15.025042
A8: ='Каталог BX-013'!A8 -> Пакет 150 | B8: ='Каталог BX-013'!B8 -> 150 | C8: ='Каталог BX-013'!C8 -> 9.5 | D8: =C8/B8 -> 0.063333333 | E8: =B8/C8 -> 15.789474
A9: ='Каталог BX-013'!A9 -> Пакет 400 | B9: ='Каталог BX-013'!B9 -> 400 | C9: ='Каталог BX-013'!C9 -> 24.99 | D9: =C9/B9 -> 0.062475 | E9: =B9/C9 -> 16.006403
A10: Мин. цена 1 FTXcoin | D10: =MIN(D5:D9) -> 0.062475
A11: Макс. цена 1 FTXcoin | D11: =MAX(D5:D9) -> 0.066555556
A13: Набор | B13: FTXcoin | C13: Эквивалент USD (мин.) | D13: Эквивалент USD (макс.)
A14: Rare Pack | B14: 39 | C14: =B14*D10 -> 2.436525 | D14: =B14*D11 -> 2.5956667
A15: Epic Pack | B15: 59 | C15: =B15*D10 -> 3.686025 | D15: =B15*D11 -> 3.9267778
A16: Legendary Pack | B16: 89 | C16: =B16*D10 -> 5.560275 | D16: =B16*D11 -> 5.9234444
A17: Immortal Pack | B17: 139 | C17: =B17*D10 -> 8.684025 | D17: =B17*D11 -> 9.2512222
A18: Elite Pack | B18: 149 | C18: =B18*D10 -> 9.308775 | D18: =B18*D11 -> 9.9167778
A19: Create Player | B19: 30 | C19: =B19*D10 -> 1.87425 | D19: =B19*D11 -> 1.9966667
A21: Лига при полном составе | B21: Мест | C21: Взносы за сезон, FTXcoin | D21: Создателю | E21: Призовой фонд | F21: Казна (sink)
A22: Fan League | B22: ='Каталог BX-013'!F33 -> 48 | C22: =B22*'Каталог BX-013'!C29 -> 240 | D22: =B22*'Каталог BX-013'!D29 -> 96 | E22: =B22*'Каталог BX-013'!E29 -> 96 | F22: =B22*'Каталог BX-013'!F29 -> 48
A23: Pro League | B23: ='Каталог BX-013'!F33 -> 48 | C23: =B23*'Каталог BX-013'!C30 -> 384 | D23: =B23*'Каталог BX-013'!D30 -> 144 | E23: =B23*'Каталог BX-013'!E30 -> 144 | F23: =B23*'Каталог BX-013'!F30 -> 96
A24: Master League | B24: ='Каталог BX-013'!F33 -> 48 | C24: =B24*'Каталог BX-013'!C31 -> 576 | D24: =B24*'Каталог BX-013'!D31 -> 240 | E24: =B24*'Каталог BX-013'!E31 -> 240 | F24: =B24*'Каталог BX-013'!F31 -> 96
A25: Взносы — внутриигровая валюта: оборот между пользователями и sink, а не денежная выручка платформы.
A27: Premium Pass | B27: USD за сезон | C27: USD в день | D27: Сезонов в год | E27: Макс. USD в год на 1 плательщика
A28: Premium Pass | B28: ='Каталог BX-013'!B14 -> 3.99 | C28: =B28/'Каталог BX-013'!C14 -> 0.285 | D28: =365/'Каталог BX-013'!C14 -> 26.071429 | E28: =B28*D28 -> 104.025

Sheet Драйверы (шаблон)
A1: Шаблон драйверной модели FootureX Game на 5 лет
A2: Жёлтые ячейки — вводы руководства (сейчас пусто). Результаты считаются формулами. Не переносится на всю компанию.
A4: Показатель | B4: Ед. | C4: Год 1 | D4: Год 2 | E4: Год 3 | F4: Год 4 | G4: Год 5 | H4: Источник / формула
A5: Аудитория (BX-008 KPI)
A6: MAU, средний | B6: чел. | H6: Требуется подтверждение
A7: DAU, средний | B7: чел. | H7: Требуется подтверждение
A8: Retention D30 | B8: % | H8: Требуется подтверждение
A9: Conversion в платящих (в месяц) | B9: % | H9: Требуется подтверждение
A10: Новые пользователи за год | B10: чел. | H10: Требуется подтверждение
A11: Денежная выручка (только Stars / TON)
A12: Платящие в месяц | B12: чел. | C12: =C6*C9 -> 0 | D12: =D6*D9 -> 0 | E12: =E6*E9 -> 0 | F12: =F6*F9 -> 0 | G12: =G6*G9 -> 0 | H12: = MAU × Conversion
A13: ARPPU в месяц | B13: USD | H13: Требуется подтверждение; цены — лист «Каталог BX-013»
A14: Месяцев коммерческой работы | B14: мес. | H14: Требуется подтверждение
A15: Покупки (Premium Pass, FTXcoin, косметика) | B15: USD | C15: =C12*C13*C14 -> 0 | D15: =D12*D13*D14 -> 0 | E15: =E12*E13*E14 -> 0 | F15: =F12*F13*F14 -> 0 | G15: =G12*G13*G14 -> 0 | H15: = платящие × ARPPU × месяцы
A16: Партнёрства, реклама, спонсорство | B16: USD | H16: Требуется подтверждение (BX-001)
A17: Revenue (валовая) | B17: USD | C17: =C15+C16 -> 0 | D17: =D15+D16 -> 0 | E17: =E15+E16 -> 0 | F17: =F15+F16 -> 0 | G17: =G15+G16 -> 0 | H17: Сумма
A18: Комиссии платформ и платёжных провайдеров | B18: % IAP | H18: Не указаны в BX — требуется подтверждение
A19: Затраты
A20: Хостинг, инфраструктура, LiveOps (прямые) | B20: USD | H20: Требуется подтверждение
A21: Gross Profit | B21: USD | C21: =C17-C15*C18-C20 -> 0 | D21: =D17-D15*D18-D20 -> 0 | E21: =E17-E15*E18-E20 -> 0 | F21: =F17-F15*F18-F20 -> 0 | G21: =G17-G15*G18-G20 -> 0 | H21: = Revenue − комиссии − прямые затраты
A22: Gross Margin | B22: % | C22: =IF(C17=0,"",C21/C17) | D22: =IF(D17=0,"",D21/D17) | E22: =IF(E17=0,"",E21/E17) | F22: =IF(F17=0,"",F21/F17) | G22: =IF(G17=0,"",G21/G17) | H22: = GP / Revenue
A23: Команда (BX-002 роли) | B23: USD | H23: Требуется подтверждение
A24: Маркетинг и привлечение (UA) | B24: USD | H24: Требуется подтверждение
A25: Прочие OPEX | B25: USD | H25: Требуется подтверждение
A26: EBITDA | B26: USD | C26: =C21-C23-C24-C25 -> 0 | D26: =D21-D23-D24-D25 -> 0 | E26: =E21-E23-E24-E25 -> 0 | F26: =F21-F23-F24-F25 -> 0 | G26: =G21-G23-G24-G25 -> 0 | H26: = GP − OPEX
A27: Амортизация | B27: USD | H27: Требуется подтверждение
A28: Налог на прибыль | B28: % | H28: Требуется подтверждение (режим IT Park — уточнить)
A29: Net Profit | B29: USD | C29: =(C26-C27)*(1-C28) -> 0 | D29: =(D26-D27)*(1-D28) -> 0 | E29: =(E26-E27)*(1-E28) -> 0 | F29: =(F26-F27)*(1-F28) -> 0 | G29: =(G26-G27)*(1-G28) -> 0 | H29: = (EBITDA − D&A) × (1 − налог)
A30: Изменение оборотного капитала | B30: USD | H30: Требуется подтверждение
A31: Operating Cash Flow | B31: USD | C31: =C29+C27-C30 -> 0 | D31: =D29+D27-D30 -> 0 | E31: =E29+E27-E30 -> 0 | F31: =F29+F27-F30 -> 0 | G31: =G29+G27-G30 -> 0 | H31: = NP + D&A − ΔWC
A32: CAPEX | B32: USD | H32: Требуется подтверждение
A33: Free Cash Flow | B33: USD | C33: =C31-C32 -> 0 | D33: =D31-D32 -> 0 | E33: =E31-E32 -> 0 | F33: =F31-F32 -> 0 | G33: =G31-G32 -> 0 | H33: = OCF − CAPEX
A34: Накопленный FCF | B34: USD | C34: =C33 -> 0 | D34: =C34+D33 -> 0 | E34: =D34+E33 -> 0 | F34: =E34+F33 -> 0 | G34: =F34+G33 -> 0 | H34: Нарастающим итогом
A35: Юнит-экономика
A36: CAC | B36: USD | C36: =IF(C10=0,"",C24/C10) | D36: =IF(D10=0,"",D24/D10) | E36: =IF(E10=0,"",E24/E10) | F36: =IF(F10=0,"",F24/F10) | G36: =IF(G10=0,"",G24/G10) | H36: = UA / новые пользователи
A37: Средний срок жизни платящего | B37: мес. | H37: Требуется подтверждение
A38: LTV платящего | B38: USD | C38: =C13*(1-C18)*C37 -> 0 | D38: =D13*(1-D18)*D37 -> 0 | E38: =E13*(1-E18)*E37 -> 0 | F38: =F13*(1-F18)*F37 -> 0 | G38: =G13*(1-G18)*G37 -> 0 | H38: = ARPPU × (1 − комиссия) × срок жизни
A39: ROI (накопленный) | B39: % | H39: Считается после ввода инвестиций

Sheet Классификация
A1: Классификация данных презентации
A2: Правило 13 консолидированного ТЗ
A4: Категория | B4: Примеры | C4: Как показано
A5: Реальные данные (документы) | B5: Цены BX-013; структура экономики BX-003; этапы BX-001/BX-008; роли BX-002 | C5: Статус «Документы BX», ссылка на документ
A6: Расчёт по данным BX | B6: Цена 1 FTXcoin по пакетам; USD-эквивалент наборов; распределение взносов лиги; Premium Pass в день | C6: Статус «Расчёт по данным BX», формулы в Excel
A7: Требует подтверждения | B7: MAU/DAU, конверсия, ARPPU, выручка, затраты, инвестиции, окупаемость, даты, комиссии | C7: Статус «Цифры не предоставлены» / «Требуется подтверждение», пустые ячейки
